{
  "name": "All Purpose Seasoning",
  "description": "A versatile, salt-free seasoning blend for meats and savory dishes like sautéed vegetables. Keeping salt separate allows better control of seasoning, especially in dishes that already contain salty ingredients.",
  "gist": "Equal parts smoked paprika, garlic powder, and onion powder, with half a part black pepper.",
  "ingredients": "- 1 part smoked paprika\n- 1 part garlic powder\n- 1 part onion powder\n- 1/2 part black pepper",
  "steps": "1. Combine all ingredients.\n2. Optionally, add half part cayenne or chili powder for more spice, or half part any dried herbs like oregano or thyme.",
  "notes": ""
}
